serverless/__init__.py
serverless/aws/__init__.py
serverless/aws/alerts/__init__.py
serverless/aws/alerts/sqs.py
serverless/aws/auth.py
serverless/aws/features/__init__.py
serverless/aws/features/api_handler.py
serverless/aws/features/api_keys.py
serverless/aws/features/encryption.py
serverless/aws/features/stepfunctions.py
serverless/aws/features/xray.py
serverless/aws/functions/__init__.py
serverless/aws/functions/appsync.py
serverless/aws/functions/dynamodb.py
serverless/aws/functions/event_bridge.py
serverless/aws/functions/generic.py
serverless/aws/functions/http.py
serverless/aws/functions/kinesis.py
serverless/aws/functions/s3.py
serverless/aws/functions/sqs.py
serverless/aws/functions/websocket.py
serverless/aws/iam/__init__.py
serverless/aws/iam/apigw.py
serverless/aws/iam/dynamodb.py
serverless/aws/iam/event_bridge.py
serverless/aws/iam/kinesis.py
serverless/aws/iam/redshift.py
serverless/aws/iam/secrets_manager.py
serverless/aws/iam/sqs.py
serverless/aws/iam/xray.py
serverless/aws/provider.py
serverless/aws/resources/__init__.py
serverless/aws/resources/dynamodb.py
serverless/aws/resources/functions.py
serverless/aws/resources/iam.py
serverless/aws/resources/kinesis.py
serverless/aws/resources/kms.py
serverless/aws/resources/logs.py
serverless/aws/resources/s3.py
serverless/aws/resources/sqs.py
serverless/aws/types.py
serverless/cli.py
serverless/feature.py
serverless/integration/__init__.py
serverless/integration/event_dispatcher.py
serverless/integration/powertools.py
serverless/integration/sentry.py
serverless/plugins.py
serverless/provider.py
serverless/service/__init__.py
serverless/service/configuration.py
serverless/service/environment.py
serverless/service/functions.py
serverless/service/package.py
serverless/service/plugins/__init__.py
serverless/service/plugins/appsync/__init__.py
serverless/service/plugins/appsync/builder.py
serverless/service/plugins/appsync/plugin.py
serverless/service/plugins/appsync/resolver.py
serverless_builder-2.19.6.dist-info/LICENSE
serverless_builder-2.19.6.dist-info/METADATA
serverless_builder-2.19.6.dist-info/WHEEL
serverless_builder-2.19.6.dist-info/entry_points.txt
serverless_builder-2.19.6.dist-info/RECORD
