Metadata-Version: 2.3
Name: serverless-builder
Version: 2.19.6
Summary: Python interface to easily generate `serverless.yml`.
License: MIT
Keywords: library,serverless
Author: Epsy
Author-email: engineering@epsyhealth.com
Requires-Python: >=3.9,<4.0
Classifier: Intended Audience :: Developers
Classifier: License :: OSI Approved :: MIT License
Classifier: Programming Language :: Python
Classifier: Programming Language :: Python :: 3
Classifier: Programming Language :: Python :: 3.9
Classifier: Programming Language :: Python :: 3.10
Classifier: Programming Language :: Python :: 3.11
Classifier: Programming Language :: Python :: 3.12
Classifier: Programming Language :: Python :: 3.13
Classifier: Programming Language :: Python :: 3 :: Only
Classifier: Programming Language :: Python :: 3.8
Requires-Dist: PyYAML (>=6.0,<7.0)
Requires-Dist: awacs (>=2.1.0,<3.0.0)
Requires-Dist: inflection (>=0.5.1,<0.6.0)
Requires-Dist: pydantic-extra-types (>=2.5.0,<3.0.0)
Requires-Dist: pydantic[email] (>=2.6.1,<3.0.0)
Requires-Dist: strawberry-graphql (>=0.265.1,<0.266.0)
Requires-Dist: troposphere (>=4.0.2,<5.0.0)
Project-URL: Homepage, https://epsylabs.github.io/serverless-builder/
Project-URL: Repository, https://github.com/epsylabs/serverless-builder
